README.rst
RPiHTTPServer.py
setup.py
RPiHTTPServer.egg-info/PKG-INFO
RPiHTTPServer.egg-info/SOURCES.txt
RPiHTTPServer.egg-info/dependency_links.txt
RPiHTTPServer.egg-info/not-zip-safe
RPiHTTPServer.egg-info/top_level.txt