Metadata-Version: 1.0
Name: RPiHTTPServer
Version: 0.1.0
Summary: HTTP server and request handler built on top of BaseHTTPServer intended for Raspberry Pi projects with a web interface
Home-page: http://github.com/mauntrelio/RPiHTTPServer
Author: Maurizio Manetti
Author-email: maurizio@imanetti.net
License: MIT
Platform: UNKNOWN
